datatype_tools/__init__.py
datatype_tools/lib/Dict.py
datatype_tools/lib/Float.py
datatype_tools/lib/List.py
datatype_tools/lib/Str.py
datatype_tools/lib/__init__.py
datatype_tools/utils/__init__.py
datatype_tools/utils/dict_functions.py
datatype_tools/utils/float_functions.py
datatype_tools/utils/function_tests.py
datatype_tools/utils/list_functions.py
datatype_tools/utils/string_functions.py
datatype_tools/utils/type_functions.py
datatype_tools-0.1.3.dist-info/LICENSE
datatype_tools-0.1.3.dist-info/METADATA
datatype_tools-0.1.3.dist-info/WHEEL
datatype_tools-0.1.3.dist-info/top_level.txt
datatype_tools-0.1.3.dist-info/RECORD
