Metadata-Version: 2.1
Name: datatype-tools
Version: 0.1.3
Summary: Additional methods for Python's immutable data types.
Home-page: https://github.com/edmundpf/datatype_tools
Author: Edmund Pfeil
Author-email: edmundpf@buffalo.edu
License: UNKNOWN
Platform: UNKNOWN
Classifier: Programming Language :: Python :: 3
Classifier: License :: OSI Approved :: MIT License
Classifier: Operating System :: OS Independent
Requires-Dist: forbiddenfruit
